elasticsearchquery/__init__.py
elasticsearchquery/elasticsearchquery.py
elasticsearchquery-0.1.1.dist-info/DESCRIPTION.rst
elasticsearchquery-0.1.1.dist-info/METADATA
elasticsearchquery-0.1.1.dist-info/RECORD
elasticsearchquery-0.1.1.dist-info/WHEEL
elasticsearchquery-0.1.1.dist-info/entry_points.txt
elasticsearchquery-0.1.1.dist-info/metadata.json
elasticsearchquery-0.1.1.dist-info/top_level.txt
